usepy_plugin_redis/__init__.py
usepy_plugin_redis/store.py
usepy_plugin_redis/stream.py
usepy_plugin_redis-0.1.7.dist-info/METADATA
usepy_plugin_redis-0.1.7.dist-info/WHEEL
usepy_plugin_redis-0.1.7.dist-info/RECORD
