Metadata-Version: 2.1
Name: usepy-plugin-redis
Version: 0.1.7
Summary: 
Author: miclon
Author-email: jcnd@163.com
Requires-Python: >=3.8,<4.0
Classifier: Programming Language :: Python :: 3
Classifier: Programming Language :: Python :: 3.8
Classifier: Programming Language :: Python :: 3.9
Classifier: Programming Language :: Python :: 3.10
Classifier: Programming Language :: Python :: 3.11
Classifier: Programming Language :: Python :: 3.12
Requires-Dist: redis (>=4.6.0,<6.0.0)
